Turbulence/__init__.py
Turbulence/api.py
Turbulence/dataio.py
Turbulence/equation.py
Turbulence/statistics.py
Turbulence/test.py
Turbulence/utils.py
Turbulence/data/dbinfo.h5
Turbulence/data/channel-baryctrwt/README
Turbulence/data/channel-baryctrwt/baryctrwt-diffmat-x-r-1-fd4.dat
Turbulence/data/channel-baryctrwt/baryctrwt-diffmat-x-r-1-fd6.dat
Turbulence/data/channel-baryctrwt/baryctrwt-diffmat-x-r-1-fd8.dat
Turbulence/data/channel-baryctrwt/baryctrwt-diffmat-x-r-2-fd4.dat
Turbulence/data/channel-baryctrwt/baryctrwt-diffmat-x-r-2-fd6.dat
Turbulence/data/channel-baryctrwt/baryctrwt-diffmat-x-r-2-fd8.dat
Turbulence/data/channel-baryctrwt/baryctrwt-diffmat-y-r-1-fd4.dat
Turbulence/data/channel-baryctrwt/baryctrwt-diffmat-y-r-1-fd6.dat
Turbulence/data/channel-baryctrwt/baryctrwt-diffmat-y-r-1-fd8.dat
Turbulence/data/channel-baryctrwt/baryctrwt-diffmat-y-r-2-fd4.dat
Turbulence/data/channel-baryctrwt/baryctrwt-diffmat-y-r-2-fd6.dat
Turbulence/data/channel-baryctrwt/baryctrwt-diffmat-y-r-2-fd8.dat
Turbulence/data/channel-baryctrwt/baryctrwt-diffmat-z-r-1-fd4.dat
Turbulence/data/channel-baryctrwt/baryctrwt-diffmat-z-r-1-fd6.dat
Turbulence/data/channel-baryctrwt/baryctrwt-diffmat-z-r-1-fd8.dat
Turbulence/data/channel-baryctrwt/baryctrwt-diffmat-z-r-2-fd4.dat
Turbulence/data/channel-baryctrwt/baryctrwt-diffmat-z-r-2-fd6.dat
Turbulence/data/channel-baryctrwt/baryctrwt-diffmat-z-r-2-fd8.dat
Turbulence/data/channel-baryctrwt/baryctrwt-x-lag4.dat
Turbulence/data/channel-baryctrwt/baryctrwt-x-lag6.dat
Turbulence/data/channel-baryctrwt/baryctrwt-x-lag8.dat
Turbulence/data/channel-baryctrwt/baryctrwt-y-lag4.dat
Turbulence/data/channel-baryctrwt/baryctrwt-y-lag6.dat
Turbulence/data/channel-baryctrwt/baryctrwt-y-lag8.dat
Turbulence/data/channel-baryctrwt/baryctrwt-z-lag4.dat
Turbulence/data/channel-baryctrwt/baryctrwt-z-lag6.dat
Turbulence/data/channel-baryctrwt/baryctrwt-z-lag8.dat
Turbulence/data/channel-baryctrwt/channel_baryctrwt.c
Turbulence/data/channel-baryctrwt/grid.h5
Turbulence-1.0.5.dist-info/LICENSE
Turbulence-1.0.5.dist-info/METADATA
Turbulence-1.0.5.dist-info/WHEEL
Turbulence-1.0.5.dist-info/top_level.txt
Turbulence-1.0.5.dist-info/RECORD
