Metadata-Version: 2.1
Name: Turbulence
Version: 1.0.5
Summary: Code for Turbulence Analyze
Home-page: https://github.com/AdwardAllan
Author: Li XinJUN
Author-email: lxjproductivity@gmail.com
License: GNU License
Platform: all
Classifier: Intended Audience :: Developers
Classifier: Operating System :: OS Independent
Classifier: Natural Language :: Chinese (Simplified)
Classifier: Programming Language :: Python :: 3.8
Classifier: Topic :: Software Development :: Libraries
License-File: LICENSE
Requires-Dist: h5py
Requires-Dist: scipy
Requires-Dist: sympy
Requires-Dist: numpy
Requires-Dist: findiff
